babelbetes/__init__.py
babelbetes/run_functions.py
babelbetes/src/__init__.py
babelbetes/src/cdf.py
babelbetes/src/date_helper.py
babelbetes/src/drawing.py
babelbetes/src/file_saver.py
babelbetes/src/find_periods.py
babelbetes/src/logger.py
babelbetes/src/pandas_helper.py
babelbetes/src/postprocessing.py
babelbetes/src/tdd.py
babelbetes/studies/__init__.py
babelbetes/studies/dataset_initializer.py
babelbetes/studies/dclp.py
babelbetes/studies/flair.py
babelbetes/studies/iobp2.py
babelbetes/studies/loop.py
babelbetes/studies/pedap.py
babelbetes/studies/replacebg.py
babelbetes/studies/studydataset.py
babelbetes/studies/t1dexi.py
tests/__init__.py
tests/conftest.py
tests/test_date_helper.py
tests/test_find_periods.py
tests/test_flair.py
tests/test_iobp2.py
tests/test_pandas_helper.py
tests/test_postprocessing.py
tests/test_studydataset.py
tests/test_tdd.py
babelbetes-0.1.0.dist-info/METADATA
babelbetes-0.1.0.dist-info/WHEEL
babelbetes-0.1.0.dist-info/top_level.txt
babelbetes-0.1.0.dist-info/RECORD
