Metadata-Version: 2.4
Name: babelbetes
Version: 0.1.0
Summary: Extracting standardized tables from heterogeneous diabetes management datasets
Home-page: https://github.com/nudgebg/babelbetes
Classifier: Programming Language :: Python :: 3
Classifier: Operating System :: OS Independent
Classifier: License :: OSI Approved :: MIT License
Requires-Python: >=3, <4
Requires-Dist: numpy<2.0,>=1.26.4
Requires-Dist: pandas<3.0,>=2.2.2
Requires-Dist: pyarrow
Requires-Dist: scipy<2.0,>=1.13.0
Requires-Dist: ipykernel>=6.29.5
Requires-Dist: matplotlib<4.0,>=3.9.3
Requires-Dist: ipywidgets>=8.1.5
Requires-Dist: notebook>=7.2.2
Requires-Dist: ipympl>=0.9.4
Requires-Dist: bokeh<4.0,>=3.4.3
Requires-Dist: graphviz>=0.20.3
Requires-Dist: dask>=2024.8.0
Requires-Dist: dask-expr>=1.1.10
Requires-Dist: isodate>=0.7.2
Requires-Dist: zipfile-deflate64-macos
Provides-Extra: dev
Requires-Dist: pytest>=8.2.2; extra == "dev"
Requires-Dist: mkdocs>=1.6.1; extra == "dev"
Requires-Dist: mkdocs-material>=9.5.36; extra == "dev"
Requires-Dist: mkdocstrings-python>=1.11.1; extra == "dev"
Requires-Dist: pymdown-extensions>=10.8.1; extra == "dev"
Requires-Dist: mkdocs-with-pdf>=0.9.3; extra == "dev"
Dynamic: classifier
Dynamic: description
Dynamic: description-content-type
Dynamic: home-page
Dynamic: provides-extra
Dynamic: requires-dist
Dynamic: requires-python
Dynamic: summary
